dxel/__init__.py
dxel/datascience/__init__.py
dxel/datascience/agent/__init__.py
dxel/datascience/agent/orchestration_agent.py
dxel/datascience/utils/__init__.py
dxel/datascience/utils/data_summary_generator.py
dxel/utils/__init__.py
dxel/utils/llm/__init__.py
dxel/utils/llm/base_llm.py
dxel/utils/llm/gemini.py
dxel/utils/llm/groq.py
dxel/utils/llm_agent/__init__.py
dxel/utils/llm_agent/agent.py
dxel/utils/llm_agent/utils/__init__.py
dxel/utils/llm_agent/utils/io.py
dxel/utils/llm_agent/utils/load_agent_config.py
dxel/utils/llm_agent/utils/load_config.py
dxel/utils/llm_agent/utils/utils.py
dxel/utils/tool/__init__.py
src_v1/__init__.py
src_v1/agent/__init__.py
src_v1/agent/agent.py
src_v1/llm/__init__.py
src_v1/llm/gemini.py
src_v1/llm/openai.py
src_v1/utils/__init__.py
src_v1/utils/io.py
src_v1/utils/load_agent_config.py
src_v1/utils/load_config.py
src_v1/utils/utils.py
tests/__init__.py
tests/test_dynamic_csv.py
tests/test_gemini.py
tests/test_groq.py
dxel-0.1.0b3.dist-info/METADATA
dxel-0.1.0b3.dist-info/WHEEL
dxel-0.1.0b3.dist-info/top_level.txt
dxel-0.1.0b3.dist-info/RECORD
