Metadata-Version: 2.4
Name: dxel
Version: 0.1.0b3
Summary: An AI-powered data analysis agent for intelligent data insights and visualization
Home-page: https://github.com/prashantgavit/dxel
Author: Prashant Gavit
Author-email: prashant.gavit115@gmail.com
Keywords: data-analysis ai gemini llm agent data-science
Classifier: Intended Audience :: Developers
Classifier: Intended Audience :: Science/Research
Classifier: Topic :: Software Development :: Libraries :: Python Modules
Classifier: Topic :: Scientific/Engineering :: Artificial Intelligence
Classifier: Topic :: Scientific/Engineering :: Information Analysis
Classifier: License :: OSI Approved :: MIT License
Classifier: Programming Language :: Python :: 3
Classifier: Programming Language :: Python :: 3.11
Classifier: Operating System :: OS Independent
Requires-Python: >=3.11,<3.13
Requires-Dist: google-genai>=0.8.0
Requires-Dist: groq>=0.4.0
Requires-Dist: pandas>=2.0.0
Requires-Dist: numpy>=1.24.0
Requires-Dist: matplotlib>=3.7.0
Requires-Dist: scipy>=1.10.0
Requires-Dist: pyyaml>=6.0
Dynamic: author
Dynamic: author-email
Dynamic: classifier
Dynamic: description
Dynamic: description-content-type
Dynamic: home-page
Dynamic: keywords
Dynamic: requires-dist
Dynamic: requires-python
Dynamic: summary
